stowng/__init__.py
stowng/__main__.py
stowng/parser.py
stowng/stow.py
stowng/task.py
stowng/utils.py
stowng/data/default-ignore-list
stowng-0.0.5.dist-info/LICENSE
stowng-0.0.5.dist-info/METADATA
stowng-0.0.5.dist-info/WHEEL
stowng-0.0.5.dist-info/entry_points.txt
stowng-0.0.5.dist-info/top_level.txt
stowng-0.0.5.dist-info/RECORD
