Metadata-Version: 2.1
Name: stowng
Version: 0.0.5
Summary: GNU Stow in Python
Author-email: Andreas Himmler <andreas@himmler.me>
License: GPLv3
Project-URL: Homepage, https://github.com/Andy0n/stowng
Project-URL: Bug Tracker, https://github.com/Andy0n/stowng/issues
Classifier: Development Status :: 2 - Pre-Alpha
Classifier: Environment :: Console
Classifier: Programming Language :: Python :: 3 :: Only
Classifier: License :: OSI Approved :: GNU General Public License v3 (GPLv3)
Classifier: Operating System :: OS Independent
Classifier: Topic :: Utilities
Requires-Python: >=3.7
License-File: LICENSE
